mlex/__init__.py
mlex/analysis/__init__.py
mlex/analysis/markov_analyzer.py
mlex/analysis/markov_analyzer_plotter.py
mlex/analysis/sequence_analyzer_plotter.py
mlex/analysis/sequence_span_analyzer.py
mlex/evaluation/__init__.py
mlex/evaluation/base.py
mlex/evaluation/evaluator.py
mlex/evaluation/plotter.py
mlex/evaluation/threshold.py
mlex/evaluation/utils.py
mlex/features/__init__.py
mlex/features/columns.py
mlex/features/sequences.py
mlex/models/__init__.py
mlex/models/gru.py
mlex/models/lstm.py
mlex/models/mlp.py
mlex/models/random_forest.py
mlex/models/rnn.py
mlex/models/base_components/gru_base_model.py
mlex/models/base_components/lstm_base_model.py
mlex/models/base_components/rnn_base_model.py
mlex/utils/__init__.py
mlex/utils/analysis.py
mlex/utils/context_aware.py
mlex/utils/datareader.py
mlex/utils/noiseinjector.py
mlex/utils/preprocessing.py
mlex/utils/split.py
mlex/utils/utils.py
mlex_lib-0.0.6.dist-info/licenses/LICENSE
mlex_lib-0.0.6.dist-info/METADATA
mlex_lib-0.0.6.dist-info/WHEEL
mlex_lib-0.0.6.dist-info/top_level.txt
mlex_lib-0.0.6.dist-info/RECORD
