Metadata-Version: 2.4
Name: mlex-lib
Version: 0.0.6
Summary: Money Laundering Expert System - A machine learning framework for financial fraud detection
Author-email: Diego Pinheiro <diegompin@gmail.com>
License: MIT License
Project-URL: Homepage, https://github.com/IoTDataAtelier/mlex
Project-URL: Bug Tracker, https://github.com/IoTDataAtelier/mlex/issues
Keywords: machine-learning,fraud-detection,financial,neural-networks,gru,lstm,rnn
Classifier: Programming Language :: Python :: 3
Classifier: License :: OSI Approved :: MIT License
Classifier: Operating System :: OS Independent
Requires-Python: >=3.9
License-File: LICENSE
Requires-Dist: fastavro~=1.10.0
Requires-Dist: ipykernel~=6.29.5
Requires-Dist: matplotlib~=3.10.0
Requires-Dist: networkx~=3.4.2
Requires-Dist: numpy~=1.26.4
Requires-Dist: pandas~=2.2.3
Requires-Dist: pyarrow~=19.0.1
Requires-Dist: scikit-learn~=1.6.1
Requires-Dist: scipy~=1.11.4
Requires-Dist: seaborn~=0.13.2
Requires-Dist: shap~=0.47.0
Requires-Dist: skorch~=1.1.0
Requires-Dist: torch~=2.7.0
Provides-Extra: dev
Requires-Dist: pytest>=6.0.0; extra == "dev"
Requires-Dist: pytest-cov>=3.0.0; extra == "dev"
Requires-Dist: black>=22.0.0; extra == "dev"
Requires-Dist: flake8>=4.0.0; extra == "dev"
Requires-Dist: mypy>=0.950; extra == "dev"
Requires-Dist: pre-commit>=2.15.0; extra == "dev"
Dynamic: license-file
